{
  "hints.chars": "asdfjklweruio gh",
  "mode.normal.paste_and_go": "",
  "mode.normal.paste_and_go_in_tab": "",
  "mode.normal.scroll_right": "",
  "mode.normal.scroll_down": "",
  "mode.normal.scroll_page_down": "<c-f> <space>",
  "mode.normal.scroll_page_up": "<c-b> <s-space>",
  "mode.normal.scroll_half_page_down": "",
  "mode.normal.scroll_half_page_up": "",
  "mode.normal.tab_select_previous": "h gT",
  "mode.normal.tab_select_next": "l gt",
  "mode.normal.tab_close": "d",
  "mode.normal.tab_restore": "u"
}
